mlx_micrograd/__init__.py
mlx_micrograd/engine.py
mlx_micrograd/nn.py
mlx_micrograd-0.1.0.dist-info/METADATA
mlx_micrograd-0.1.0.dist-info/WHEEL
mlx_micrograd-0.1.0.dist-info/top_level.txt
mlx_micrograd-0.1.0.dist-info/RECORD
