Metadata-Version: 2.1
Name: mlx-micrograd
Version: 0.1.0
Summary: An mlx port of Karpathy's micrograd - a tiny scalar-valued autograd engine with a small PyTorch-like neural network library on top.
Home-page: https://github.com/Jaykef/mlx_micrograd
Author: Jaward Sesay
Author-email: jawardsesay1996@gmail.com
Classifier: Programming Language :: Python :: 3
Classifier: License :: OSI Approved :: MIT License
Requires-Python: >=3.6
Requires-Dist: mlx (>=0.8.0)
Requires-Dist: mlx-lm (>=0.4.0)
Requires-Dist: numpy
Requires-Dist: torch
